{
  "Name": "芯达通报关系统", //业务名称：芯达通报关系统
  "ID": "xdtcdms", //业务ID
  "IconUrl": "../Images/logos/logos6.png", //业务Icon链接地址
  "LogoUrl": "../Images/logos/logo6.png", //业务Logo链接地址
  "FirstUrl": "/XDT/Index.html", //业务首页地址
  "Company": "芯达通供应链",
  "Menu": [
    {
      "text": "产品预归类",
      "state": "open",
      "children": [
        {
          "text": "预处理一",
          "url": "/XDT/Classify/Icgoo/FirstListTemp.aspx"
        },
        {
          "text": "预处理二",
          "url": "/XDT/Classify/Icgoo/SecondListTemp.aspx"
        },
        {
          "text": "已完成",
          "url": "/XDT/Classify/Icgoo/DoneListTemp.aspx"
        }
      ]
    },
    {
      "text": "产品归类",
      "state": "open",
      "children": [
        {
          "text": "预处理一",
          "url": "/XDT/Classify/Outside/FirstListTemp.aspx"
        },
        {
          "text": "预处理二",
          "url": "/XDT/Classify/Outside/SecondListTemp.aspx"
        },
        {
          "text": "已完成",
          "url": "/XDT/Classify/Outside/DoneListTemp.aspx"
        }
      ]
    },
    {
      "text": "税费异常",
      "state": "open",
      "children": [
        {
          "text": "未处理",
          "url": "/CXHY/declaration/orderchange/list.aspx"
        },
        {
          "text": "已处理",
          "url": "/CXHY/declaration/orderchange/handledlist.aspx"
        }
      ]
    },
    {
      "text": "产品变更",
      "state": "open",
      "children": [
        {
          "text": "未处理",
          "url": "/CXHY/classify/productchange/unprocesslist.aspx"
        },
        {
          "text": "已处理",
          "url": "/CXHY/classify/productchange/processlist.aspx"
        }
      ]
    },
    {
      "text": "报关通知",
      "state": "open",
      "children": [
        {
          "text": "待制单",
          "url": "/XDT/Declaration/Notice/List.aspx"
        },
        {
          "text": "已制单",
          "url": "/XDT/Declaration/Notice/SearchList.aspx"
        }
      ]
    },
    {
      "text": "报关单管理",
      "state": "open",
      "children": [
        {
          "text": "草稿",
          "url": "/XDT/Declaration/Declare/List.aspx"
        },
        {
          "text": "已申报",
          "url": "/XDT/Declaration/Declare/MakedList.aspx"
        },
        {
          "text": "上传报关单",
          "url": "/XDT/Declaration/Declare/UnUploadedList.aspx"
        },
        {
          "text": "表格申报",
          "url": "/XDT/Declaration/Declare/ExcelList.aspx"
        }
      ]
    },
    {
      "text": "舱单管理",
      "state": "open",
      "children": [
        {
          "text": "草稿",
          "url": "/XDT/Declaration/Manifest/List.aspx"
        },
        {
          "text": "已申报",
          "url": "/XDT/Declaration/Manifest/MakedList.aspx"
        }
      ]
    },
    {
      "text": "物流管理",
      "state": "open",
      "children": [
        {
          "text": "承运商",
          "url": "/XDT/Logistics/Carrier/List.aspx"
        },
        {
          "text": "司机管理",
          "url": "/XDT/Logistics/Driver/List.aspx"
        },
        {
          "text": "车辆管理",
          "url": "/XDT/Logistics/Vehicle/List.aspx"
        },
        {
          "text": "运输批次",
          "url": "/XDT/Logistics/ManifestVoyage/list.aspx"
        }
      ]
    }
  ]
}
